anchor.py
pythonista_anchor-1.0.dist-info/LICENSE
pythonista_anchor-1.0.dist-info/WHEEL
pythonista_anchor-1.0.dist-info/METADATA
pythonista_anchor-1.0.dist-info/RECORD
