Metadata-Version: 2.1
Name: pythonista-anchor
Version: 1.0
Summary: Pythonista UI layouts using relative constraints instead of coordinate
Home-page: https://github.com/mikaelho/pythonista-uiconstraints
License: TheUnlicense
Author: Mikael Honkala
Author-email: mikael.honkala@gmail.com
Classifier: Operating System :: iOS
